<?xml version="1.0" encoding="utf-8"?>
<users>
  <user>
    <id>3</id>
    <username>JKLApprover</username>
    <firstname>Hyväksyjä</firstname>
    <lastname>Jyväskylä</lastname>
    <department>Talous</department>
    <email>hyvaksyja.jyvaskyla@je.com</email>
    <roles>
      <role>approver</role>
    </roles>
  </user>
  <user>
    <id>2</id>
    <username>TREApprover</username>
    <firstname>Hyväksyjä</firstname>
    <lastname>Tampere</lastname>
    <department>Talous</department>
    <email>hyvaksyja.tampere@je.com</email>
    <roles>
      <role>approver</role>
    </roles>
  </user>
  <user>
    <id>1</id>
    <username>jheikkil</username>
    <firstname>Juha</firstname>
    <lastname>Heikkilä</lastname>
    <department>Notes-tiimi</department>
    <email>juha.heikkila@solteq.com</email>
    <roles>
      <role>admin</role>
      <role>approver</role>
      <role>author</role>
      <role>debug</role>
    </roles>
  </user>
  <user>
    <id>4</id>
    <username>HKIApprover</username>
    <firstname>Hyväksyjä</firstname>
    <lastname>Helsinki</lastname>
    <department>Talous</department>
    <email>hyvaksyja.helsinki@je.com</email>
    <roles>
      <role>approver</role>
    </roles>
  </user>
</users>